[
  {
    "name":"registerseller",
    "dependson":[]
  },
  {
    "name":"registerbuyer",
    "dependson":[]
  },
  {
    "name":"unregisterbuyer",
    "dependson":[
      {
        "op":"registerbuyer",
        "params":[
        {
          "param":"buyer"
        }
        ]
      }
    ]
  },
  {
    "name":"placebid",
    "dependson":[
      {
        "op":"registerbuyer",
        "params":[
        {
          "param":"buyer"
        }
        ]
      },
      {
        "op":"unregisterbuyer",
        "params":[
        {
          "param":"buyer"
        }
        ]
      },
      {
        "op":"startauction",
        "params":[
        {
          "param":"auction"
        }
        ]
      }
    ]
  },
  {
    "name":"closeauction",
    "dependson":[
      {
        "op":"placebid",
        "params":[
        {
          "param":"auction"
        }
        ]
      },
      {
        "op":"removebid",
        "params":[
        {
          "param":"auction"
        }
        ]
      },
      {
        "op":"startauction",
        "params":[
        {
          "param":"auction"
        }
        ]
      }
    ]
  },
  {
    "name":"removebid",
    "dependson":[
      {
        "op":"placebid",
        "params":[
        {
          "param":"bid"
        }
        ]
      }
    ]
  },
  {
    "name":"addproduct",
    "dependson":[
      {
        "op":"registerseller",
        "params":[
        {
          "param":"seller"
        }
        ]
      },
      {
        "op":"unregisterseller",
        "params":[
        {
          "param":"seller"
        }
        ]
      }
    ]
  },
  {
    "name":"unregisterseller",
    "dependson":[
      {
        "op":"registerseller",
        "params":[
        {
          "param":"seller"
        }
        ]
      }
    ]
  },
  {
    "name":"createauction",
    "dependson":[
      {
        "op":"registerseller",
        "params":[
        {
          "param":"seller"
        }
        ]
      },
      {
        "op":"unregisterseller",
        "params":[
        {
          "param":"seller"
        }
        ]
      }
    ]
  },
  {
    "name":"removefromlot",
    "dependson":[
      {
        "op":"addtolot",
        "params":[
        {
          "param":"auction"
        }
        ]
      }
    ]
  },
  {
    "name":"startauction",
    "dependson":[
      {
        "op":"addtolot",
        "params":[
        {
          "param":"auction"
        }
        ]
      },
      {
        "op":"removefromlot",
        "params":[
        {
          "param":"auction"
        }
        ]
      },
      {
        "op":"createauction",
        "params":[
        {
          "param":"auction"
        }
        ]
      }
    ]
  },
  {
    "name":"addtolot",
    "dependson":[
      {
        "op":"createauction",
        "params":[
        {
          "param":"auction"
        }
        ]
      },
      {
        "op":"addproduct",
        "params":[
        {
          "param":"product"
        }
        ]
      },
      {
        "op":"removeproduct",
        "params":[
        {
          "param":"product"
        }
        ]
      }
    ]
  },
  {
    "name":"removeproduct",
    "dependson":[
      {
        "op":"addproduct",
        "params":[
        {
          "param":"product"
        }
        ]
      }
    ]
  },
  {
    "name":"removeauction",
    "dependson":[
      {
        "op":"createauction",
        "params":[
        {
          "param":"auction"
        }
        ]
      }
    ]
  }
]